scslabs/__init__.py
ScsLabs-0.0.6.dist-info/LICENSE
ScsLabs-0.0.6.dist-info/METADATA
ScsLabs-0.0.6.dist-info/WHEEL
ScsLabs-0.0.6.dist-info/top_level.txt
ScsLabs-0.0.6.dist-info/RECORD
