Metadata-Version: 2.1
Name: ScsLabs
Version: 0.0.6
Summary: Tools to make it easier for Python beginners
Home-page: UNKNOWN
Author: TomsDroid (Tomy Aliyansyah)
Author-email: <tomsdroid@kingeagle.tech>
License: UNKNOWN
Keywords: scs python,pyhon,scs,skull cyber security,pyhon indoneisa,information gathering
Platform: UNKNOWN
Classifier: Development Status :: 1 - Planning
Classifier: Intended Audience :: Developers
Classifier: Programming Language :: Python :: 3
Classifier: Operating System :: Unix
Classifier: Operating System :: MacOS :: MacOS X
Classifier: Operating System :: Microsoft :: Windows
Requires-Dist: bs4
Requires-Dist: requests
